simple_strop/__init__.py
simple_strop/operations.py
simple_strop/test_operations.py
simple_strop/test_utils.py
simple_strop/utils.py
simple_strop_david.mash-1.0.7.dist-info/LICENSE
simple_strop_david.mash-1.0.7.dist-info/METADATA
simple_strop_david.mash-1.0.7.dist-info/WHEEL
simple_strop_david.mash-1.0.7.dist-info/top_level.txt
simple_strop_david.mash-1.0.7.dist-info/RECORD
