Metadata-Version: 2.1
Name: simple-strop-david.mash
Version: 1.0.7
Summary: A simple python package to demo CI/CD pipelines
Home-page: https://gitlab.com/wonsun.ahn/simple-python-package
Author: Wonsun Ahn
Author-email: wonsun.ahn@gmail.com
License: UNKNOWN
Platform: UNKNOWN
Classifier: Programming Language :: Python :: 3
Classifier: License :: OSI Approved :: MIT License
Classifier: Operating System :: OS Independent
Requires-Python: >=3.8
License-File: LICENSE
